{
  "$schema": "jtbd-registry-v1",
  "$metadata": {
    "document_id": "JTBD-REG-001",
    "version": "1.0.0",
    "created_at": "2026-02-16T08:37:30Z",
    "updated_at": "2026-02-16T15:30:00Z",
    "generated_by": "Discovery_GenerateJTBD",
    "system_name": "Ragus",
    "stage": "Discovery",
    "checkpoint": 4
  },
  "items": [
    {
      "id": "JTBD-1.1",
      "title": "Process Urgent Patients Instantly",
      "statement": "When a trauma or critical patient arrives at the ER, I want to complete intake registration in under 30 seconds, so I can prevent dangerous delays during life-threatening situations.",
      "persona": "P-1.1",
      "persona_name": "Intake Nurse (Jenny)",
      "frequency": "Daily",
      "importance": "Critical",
      "current_satisfaction": 2,
      "pain_points": ["PP-1.1"],
      "job_type": "Functional"
    },
    {
      "id": "JTBD-1.2",
      "title": "Work Effectively with Gloves",
      "statement": "When processing patients while wearing gloves or with sanitized hands, I want to interact with the UI without removing gloves, so I can maintain infection control protocols and avoid workflow disruptions.",
      "persona": "P-1.1",
      "persona_name": "Intake Nurse (Jenny)",
      "frequency": "Daily",
      "importance": "High",
      "current_satisfaction": 2,
      "pain_points": ["PP-1.3"],
      "job_type": "Functional"
    },
    {
      "id": "JTBD-1.3",
      "title": "Use Keyboard Navigation Exclusively",
      "statement": "When entering patient data during high-volume periods, I want to use tab-enter navigation exclusively, so I can process patients without touching the mouse and maximize speed.",
      "persona": "P-1.1",
      "persona_name": "Intake Nurse (Jenny)",
      "frequency": "Daily",
      "importance": "High",
      "current_satisfaction": 3,
      "pain_points": ["PP-1.1"],
      "job_type": "Functional"
    },
    {
      "id": "JTBD-1.4",
      "title": "Escalate Trauma Cases Immediately",
      "statement": "When a trauma patient arrives requiring immediate doctor attention, I want to bypass normal intake workflow with one click, so I can get the patient to clinical staff instantly without data entry delays.",
      "persona": "P-1.1",
      "persona_name": "Intake Nurse (Jenny)",
      "frequency": "Daily",
      "importance": "Critical",
      "current_satisfaction": 3,
      "pain_points": ["PP-1.1"],
      "job_type": "Functional"
    },
    {
      "id": "JTBD-1.5",
      "title": "Mark Patients Who Leave Without Being Seen",
      "statement": "When a patient leaves the waiting room before being triaged, I want to mark them as 'LWBS' (Left Without Being Seen) in one click, so I can prevent backlog confusion and maintain accurate queue status.",
      "persona": "P-1.1",
      "persona_name": "Intake Nurse (Jenny)",
      "frequency": "Daily",
      "importance": "High",
      "current_satisfaction": 3,
      "pain_points": ["PP-1.2"],
      "job_type": "Functional"
    },
    {
      "id": "JTBD-1.6",
      "title": "Work Comfortably During Night Shifts",
      "statement": "When working night shifts in a dimly lit ER, I want to use a dark mode interface, so I can reduce eye strain and avoid screen brightness discomfort during 12-hour shifts.",
      "persona": "P-1.1",
      "persona_name": "Intake Nurse (Jenny)",
      "frequency": "Weekly",
      "importance": "Medium",
      "current_satisfaction": 1,
      "pain_points": ["PP-4.1"],
      "job_type": "Emotional"
    },
    {
      "id": "JTBD-2.1",
      "title": "Identify Next Patient Instantly",
      "statement": "When I complete triage for one patient, I want to see the next patient in queue immediately without searching, so I can prevent bottlenecks and maintain efficient patient flow.",
      "persona": "P-1.2",
      "persona_name": "Triage Nurse (Carol)",
      "frequency": "Daily",
      "importance": "High",
      "current_satisfaction": 2,
      "pain_points": ["PP-1.2"],
      "job_type": "Functional"
    },
    {
      "id": "JTBD-2.2",
      "title": "Capture Vitals Quickly with Gloves",
      "statement": "When taking patient vitals while wearing gloves, I want to enter BP, HR, O2, and Temp values with large touch targets, so I can maintain infection control without slowing workflow.",
      "persona": "P-1.2",
      "persona_name": "Triage Nurse (Carol)",
      "frequency": "Daily",
      "importance": "High",
      "current_satisfaction": 2,
      "pain_points": ["PP-1.3"],
      "job_type": "Functional"
    },
    {
      "id": "JTBD-2.3",
      "title": "Assign Initial ESI Level",
      "statement": "When completing triage assessment, I want to assign an ESI (Emergency Severity Index) level using large, color-coded buttons, so I can quickly communicate patient acuity to the doctor.",
      "persona": "P-1.2",
      "persona_name": "Triage Nurse (Carol)",
      "frequency": "Daily",
      "importance": "High",
      "current_satisfaction": 3,
      "pain_points": ["PP-1.2"],
      "job_type": "Functional"
    },
    {
      "id": "JTBD-2.4",
      "title": "Add Clinical Context for Doctor",
      "statement": "When I observe concerning patient behavior or clinical indicators, I want to add free-text contextual notes, so the doctor has qualitative information beyond vitals and ESI scores.",
      "persona": "P-1.2",
      "persona_name": "Triage Nurse (Carol)",
      "frequency": "Daily",
      "importance": "High",
      "current_satisfaction": 3,
      "pain_points": ["PP-5.2"],
      "job_type": "Functional"
    },
    {
      "id": "JTBD-2.5",
      "title": "Onboard Float Staff Without Training",
      "statement": "When regular staff are on vacation and float nurses arrive, I want them to use the system effectively within 30 seconds, so we don't experience workflow disruption or errors due to unfamiliarity.",
      "persona": "P-1.2",
      "persona_name": "Triage Nurse (Carol)",
      "frequency": "Weekly",
      "importance": "High",
      "current_satisfaction": 2,
      "pain_points": ["PP-4.3"],
      "job_type": "Functional"
    },
    {
      "id": "JTBD-2.6",
      "title": "Work Comfortably During Night Shifts",
      "statement": "When working night shifts in a dimly lit triage room, I want to use a dark mode interface, so I can reduce eye strain and avoid burning eyes after 12-hour shifts.",
      "persona": "P-1.2",
      "persona_name": "Triage Nurse (Carol)",
      "frequency": "Weekly",
      "importance": "Medium",
      "current_satisfaction": 1,
      "pain_points": ["PP-4.1"],
      "job_type": "Emotional"
    },
    {
      "id": "JTBD-3.1",
      "title": "Maintain Full Manual Control Over Prioritization",
      "statement": "When evaluating triaged patients, I want to manually assign wait time slots based on clinical judgment, so I can prevent automated systems from overriding critical medical decisions.",
      "persona": "P-1.3",
      "persona_name": "Triage Doctor (Dr. Evans)",
      "frequency": "Daily",
      "importance": "Critical",
      "current_satisfaction": 2,
      "pain_points": ["PP-5.2"],
      "job_type": "Functional"
    },
    {
      "id": "JTBD-3.2",
      "title": "Visualize Patient Flow via Kanban Board",
      "statement": "When managing patient flow throughout my shift, I want to see all patients organized in time-based columns, so I can prioritize evaluations and drag-and-drop patients as conditions change.",
      "persona": "P-1.3",
      "persona_name": "Triage Doctor (Dr. Evans)",
      "frequency": "Daily",
      "importance": "Critical",
      "current_satisfaction": 2,
      "pain_points": ["PP-3.2"],
      "job_type": "Functional"
    },
    {
      "id": "JTBD-3.3",
      "title": "See Real-Time Wait Time Alerts",
      "statement": "When patients approach or exceed their assigned wait time thresholds, I want to receive visual alerts, so I can re-evaluate prioritization before conditions escalate.",
      "persona": "P-1.3",
      "persona_name": "Triage Doctor (Dr. Evans)",
      "frequency": "Daily",
      "importance": "High",
      "current_satisfaction": 1,
      "pain_points": ["PP-3.2"],
      "job_type": "Functional"
    },
    {
      "id": "JTBD-3.4",
      "title": "Update Public Display Instantly",
      "statement": "When I assign or update a patient's wait time slot, I want the change to appear on the public waiting room display within 1 second, so patients don't confront staff due to perceived lag.",
      "persona": "P-1.3",
      "persona_name": "Triage Doctor (Dr. Evans)",
      "frequency": "Daily",
      "importance": "Critical",
      "current_satisfaction": 2,
      "pain_points": ["PP-3.2"],
      "job_type": "Functional"
    },
    {
      "id": "JTBD-3.5",
      "title": "Bulk Update Patients When Beds Open",
      "statement": "When trauma beds become available, I want to select multiple 'Immediate' patients and move them to 'With Doctor' status at once, so I can efficiently manage patient flow during bed turnover.",
      "persona": "P-1.3",
      "persona_name": "Triage Doctor (Dr. Evans)",
      "frequency": "Daily",
      "importance": "High",
      "current_satisfaction": 1,
      "pain_points": ["PP-1.2"],
      "job_type": "Functional"
    },
    {
      "id": "JTBD-3.6",
      "title": "Flag Patients for Security",
      "statement": "When I identify a patient exhibiting aggressive or unpredictable behavior, I want to flag them for security coordination, so staff are aware of potential safety risks without displaying this on the public board.",
      "persona": "P-1.3",
      "persona_name": "Triage Doctor (Dr. Evans)",
      "frequency": "Weekly",
      "importance": "High",
      "current_satisfaction": 3,
      "pain_points": ["PP-5.2"],
      "job_type": "Functional"
    },
    {
      "id": "JTBD-3.7",
      "title": "Work on Desktop and Tablet Seamlessly",
      "statement": "When moving between command center (desktop) and mobile triage (tablet), I want the same workflow and UI, so I don't have to learn device-specific interactions.",
      "persona": "P-1.3",
      "persona_name": "Triage Doctor (Dr. Evans)",
      "frequency": "Daily",
      "importance": "Medium",
      "current_satisfaction": 2,
      "pain_points": ["PP-1.3"],
      "job_type": "Functional"
    },
    {
      "id": "JTBD-4.1",
      "title": "Ensure Patients Recognize Their ID",
      "statement": "When patients wait for triage or treatment, I want them to recognize their identifier on the public display, so they feel acknowledged and human rather than just a number.",
      "persona": "P-2.1",
      "persona_name": "Patient Rights Representative (Linda)",
      "frequency": "Daily",
      "importance": "Critical",
      "current_satisfaction": 2,
      "pain_points": ["PP-2.2"],
      "job_type": "Emotional"
    },
    {
      "id": "JTBD-4.2",
      "title": "Reduce Patient Anxiety with Safe Wait Time Communication",
      "statement": "When displaying wait times to patients, I want to use category-based messaging (e.g., '30-minute wait') instead of countdown timers, so patients don't become confrontational when times expire.",
      "persona": "P-2.1",
      "persona_name": "Patient Rights Representative (Linda)",
      "frequency": "Daily",
      "importance": "Critical",
      "current_satisfaction": 1,
      "pain_points": ["PP-5.1"],
      "job_type": "Functional"
    },
    {
      "id": "JTBD-4.3",
      "title": "Maintain Privacy Compliance on Public Display",
      "statement": "When displaying patient status information, I want to ensure no GDPR or HIPAA violations occur, so the hospital avoids legal liability and protects patient privacy.",
      "persona": "P-2.1",
      "persona_name": "Patient Rights Representative (Linda)",
      "frequency": "Daily",
      "importance": "Critical",
      "current_satisfaction": 1,
      "pain_points": ["PP-2.1"],
      "job_type": "Functional"
    },
    {
      "id": "JTBD-4.4",
      "title": "Create Calming Visual Environment",
      "statement": "When patients and families wait in the ER during night hours, I want the public display to use dark mode, so we reduce sensory overload in an already stressful environment.",
      "persona": "P-2.1",
      "persona_name": "Patient Rights Representative (Linda)",
      "frequency": "Daily",
      "importance": "Medium",
      "current_satisfaction": 1,
      "pain_points": ["PP-4.2"],
      "job_type": "Emotional"
    },
    {
      "id": "JTBD-4.5",
      "title": "Enable Family Tracking of Patient Progress",
      "statement": "When family members wait in the lobby, I want them to track their loved one's progress via the patient ID, so they feel informed and reassured without violating privacy.",
      "persona": "P-2.1",
      "persona_name": "Patient Rights Representative (Linda)",
      "frequency": "Daily",
      "importance": "High",
      "current_satisfaction": 3,
      "pain_points": ["PP-2.2"],
      "job_type": "Social"
    },
    {
      "id": "JTBD-5.1",
      "title": "Ensure System Works During Internet Outages",
      "statement": "When internet connectivity is lost during storms or outages, I want the system to continue operating on the internal LAN, so we don't lose patient queue data or disrupt clinical workflow.",
      "persona": "P-2.2",
      "persona_name": "IT & Compliance Lead (Marcus)",
      "frequency": "Seasonal",
      "importance": "Critical",
      "current_satisfaction": 1,
      "pain_points": ["PP-3.1"],
      "job_type": "Functional"
    },
    {
      "id": "JTBD-5.2",
      "title": "Deploy Updates Manually Without Vendor VPN",
      "statement": "When a new system release is ready, I want to deploy it manually via tarball delivery, so I don't need to wait 2 weeks for vendor VPN approval.",
      "persona": "P-2.2",
      "persona_name": "IT & Compliance Lead (Marcus)",
      "frequency": "Monthly",
      "importance": "Medium",
      "current_satisfaction": 3,
      "pain_points": ["PP-6.1"],
      "job_type": "Functional"
    },
    {
      "id": "JTBD-5.3",
      "title": "Enforce GDPR/HIPAA Compliance",
      "statement": "When auditing system compliance, I want to verify patient data privacy controls, so we avoid legal liability and regulatory violations.",
      "persona": "P-2.2",
      "persona_name": "IT & Compliance Lead (Marcus)",
      "frequency": "Daily",
      "importance": "Critical",
      "current_satisfaction": 2,
      "pain_points": ["PP-2.1"],
      "job_type": "Functional"
    },
    {
      "id": "JTBD-5.4",
      "title": "Manage LDAP Authentication and Role-Based Access",
      "statement": "When onboarding new staff or assigning system access, I want to integrate with Active Directory for authentication and enforce role-based access control, so clinical staff have write access and public displays have view-only access.",
      "persona": "P-2.2",
      "persona_name": "IT & Compliance Lead (Marcus)",
      "frequency": "Weekly",
      "importance": "High",
      "current_satisfaction": 3,
      "pain_points": ["PP-6.2"],
      "job_type": "Functional"
    },
    {
      "id": "JTBD-5.5",
      "title": "Mitigate Session Timeout Data Loss",
      "statement": "When staff are interrupted during data entry and the 15-minute session timeout occurs, I want partially completed forms to be autosaved, so staff don't lose work and have to re-enter data.",
      "persona": "P-2.2",
      "persona_name": "IT & Compliance Lead (Marcus)",
      "frequency": "Daily",
      "importance": "Medium",
      "current_satisfaction": 2,
      "pain_points": ["PP-6.2"],
      "job_type": "Functional"
    }
  ],
  "summary": {
    "total_jtbd": 28,
    "by_importance": {
      "Critical": 10,
      "High": 12,
      "Medium": 6
    },
    "by_job_type": {
      "Functional": 23,
      "Emotional": 4,
      "Social": 1
    },
    "by_persona": {
      "P-1.1": 6,
      "P-1.2": 6,
      "P-1.3": 7,
      "P-2.1": 5,
      "P-2.2": 5
    }
  }
}
